{
  "9": [
    {
      "text": "ОРГАНИЗАЦИЯ ОЦЕНКИ УЩЕРБА ОТ ДТП; ВЗЫСКАНИЕ УЩЕРБА ОТ ДТП; ПРЕДСТАВИТЕЛЬСТВО В СУДЕ. 89115989490"
    },
    [
      {
        "text": "<br>cообщecтво \"cплeтни КОТЛaca и КОРЯЖМЫ\" - [club85841671|ПОДПИcaТЬcЯ] https://vk.com/photo221119403_355521453",
        "from_id": 189920122,
        "reply_to_uid": 0
      }
    ]
  ],
  "10": [
    {
      "text": "СООБЩЕСТВО \"Сплетни Котласа и Коряжмы\" - [club85841671|перейти]"
    },
    [
      {
        "text": "<br>cООБЩecТВО \"cПЛeТНИ КОТЛaca И КОРЯЖМЫ\" - [club85841671|подпиcaтьcя] https://vk.com/photo221119403_355521475",
        "from_id": 189920122,
        "reply_to_uid": 0
      }
    ]
  ],
  "1": [
    {
      "text": "сольвычнегодск самый лудший санаторий в мире"
    },
    [
      {
        "text": "СОГЛАСЕН!!!!!!!!!!!",
        "from_id": 55420335,
        "reply_to_uid": 0
      },
      {
        "text": "согласен но в бобровниково лучше",
        "from_id": 137200777,
        "reply_to_uid": 0
      }
    ]
  ]
}