{
  "16": [
    {
      "text": "Уважаемые одногруппники!<br>Большая просьба к инициативной группе, впредь, предупреждать об отмене мероприятия.<br>Отдельное спасибо и лучи ярости Диме Срывкову и его \"живому\" телефону."
    },
    [
      {
        "reply_to_uid": 0,
        "from_id": 2677724,
        "text": "ололо"
      }
    ]
  ],
  "2": [
    {
      "text": "Всех ждем, а то очень давно Климанчика не видел никто)))))))))"
    },
    [
      {
        "reply_to_uid": 0,
        "from_id": 1649136,
        "text": "я тут.. все впордяке.."
      },
      {
        "reply_to_uid": 0,
        "from_id": 1649136,
        "text": "я тут.. все впордяке.."
      }
    ]
  ],
  "6": [
    {
      "text": "ЭЭЭх, у меня 29го корпоративв подмосковье(("
    },
    [
      {
        "reply_to_uid": 0,
        "from_id": 1281549,
        "text": "Лерочка, я без тебя не пойду.))"
      },
      {
        "reply_to_uid": 0,
        "from_id": 464230,
        "text": "и у меня корпоратив((("
      },
      {
        "reply_to_uid": 0,
        "from_id": 2677724,
        "text": "а у меня 26ого :р ))"
      },
      {
        "reply_to_uid": 0,
        "from_id": 1551719,
        "text": "А я в Финляндии с Полей была )"
      }
    ]
  ]
}