{
  "65": [
    {
      "text": "Внимание внимание внимание!!!!! Имеет смысл приходить к 22 а не к 21 часу)"
    },
    [
      {
        "reply_to_uid": 0,
        "from_id": 1365547,
        "text": "обнови время в группе!!"
      }
    ]
  ],
  "75": [
    {
      "text": "Спасибо всем кто пришел) Может получилось не очень бодро, но вы все приняли участие в исполнение моей мечты) СПАСИБО БРО)"
    },
    [
      {
        "reply_to_uid": 0,
        "from_id": 1931933,
        "text": "Мы охуенно время провели, спасибо!"
      },
      {
        "reply_to_uid": 0,
        "from_id": 44089393,
        "text": "да!!!!<br>http://25.media.tumblr.com/tumblr_lr60rpqUHX1qei4dzo1_r2_500.gif"
      }
    ]
  ],
  "68": [
    {
      "text": "."
    },
    [
      {
        "reply_to_uid": 0,
        "from_id": 579887,
        "text": "Я мин 20 уже играю &gt;&lt;"
      }
    ]
  ],
  "5": [
    {
      "text": "Ура)))<br>Спасибо за приглашение. А праздновать где будешь? Проектируемый пр №890 73ж??"
    },
    [
      {
        "reply_to_uid": 0,
        "from_id": 4811273,
        "text": "Да , это арт пространство Башня."
      }
    ]
  ],
  "8": [
    {
      "text": "My WishList todesjsmith"
    },
    [
      {
        "reply_to_uid": 0,
        "from_id": 43494205,
        "text": "Прикольная трубочка,но дерево круче."
      },
      {
        "reply_to_uid": 0,
        "from_id": 4811273,
        "text": "удиви меня)"
      }
    ]
  ],
  "41": [
    {
      "text": "Мне нужно знать сколько будет народа."
    },
    [
      {
        "reply_to_uid": 0,
        "from_id": 4375571,
        "text": "Я нажал да но он не засчитал)"
      }
    ]
  ],
  "43": [
    {
      "text": "а музло будет играть?это все же клуб или бар?"
    },
    [
      {
        "reply_to_uid": 0,
        "from_id": 4811273,
        "text": "Музло будет с плеера , так что если будут пожелания приноси свою музыку))"
      },
      {
        "reply_to_uid": 0,
        "from_id": 4375571,
        "text": "А поболтать норм будет или будет музыка ебашить?"
      },
      {
        "reply_to_uid": 0,
        "from_id": 9276616,
        "text": "можно без фанатизма громкость ставить Олежек)"
      },
      {
        "reply_to_uid": 0,
        "from_id": 4811273,
        "text": "Это домашние посиделки , только не дома и с платным баром)"
      }
    ]
  ],
  "16": [
    {
      "text": "Еще один клуб на Проектируемом проезде))) Можно брать людей с собой?)"
    },
    [
      {
        "reply_to_uid": 0,
        "from_id": 4811273,
        "text": "Можно)"
      }
    ]
  ],
  "49": [
    {
      "text": "Эй, с днем рожденьюшки тебя!:))) Спасибо, что позвал, завтра будем у тебя в башне;)"
    },
    [
      {
        "reply_to_uid": 0,
        "from_id": 4811273,
        "text": "Спасибки ура)"
      }
    ]
  ],
  "51": [
    {
      "text": "Я до 11 работаю, меня смоджет кто нить зацепить попозже? а то у меня топографический критинизм)"
    },
    [
      {
        "reply_to_uid": 0,
        "from_id": 154072166,
        "text": "давай с тобой встретимся, будем искать вместе)) карту распечатаю"
      },
      {
        "reply_to_uid": 0,
        "from_id": 4811273,
        "text": "Уху жду жду жду)"
      },
      {
        "reply_to_uid": 0,
        "from_id": 1762759,
        "text": "я вероятно тоже собирусь только к 11 и присоединюсь к тебе)"
      },
      {
        "reply_to_uid": 0,
        "from_id": 1762759,
        "text": "ой блять да там идти надо, в общем вечером завтра договоримся я с тобой пойду))"
      },
      {
        "reply_to_uid": 0,
        "from_id": 2034522,
        "text": "гыгы)) у меня тоже географический кретинизм, если я буду опаздывать и соберусь примерно к этому времени - то позвоню вам))"
      },
      {
        "reply_to_uid": 0,
        "from_id": 151539254,
        "text": "о заебись) я на курской заканчиваю, можем прям во фрайдисе втсретиться,я вас дессертом и кофе угощу)"
      },
      {
        "reply_to_uid": 0,
        "from_id": 154072166,
        "text": "я может с Лизой и Сашей, даж скорее так, в любом случае отпишу тебе))"
      },
      {
        "reply_to_uid": 0,
        "from_id": 151539254,
        "text": "я заболела)"
      }
    ]
  ],
  "20": [
    {
      "text": ""
    },
    [
      {
        "reply_to_uid": 0,
        "from_id": 1475199,
        "text": "фига себе, когда я вырасту и стану большой, я тоже открою ночной клуб в таком месте"
      },
      {
        "reply_to_uid": 0,
        "from_id": 1475199,
        "text": "и он обязательно будет по похожему адресу, что-нибудь вроде Недостроенное мегаштрассе шоссе-Л4987, здание 33,стр.876, вход через подземные катакомбы справа от желелной двери в стене"
      },
      {
        "reply_to_uid": 0,
        "from_id": 4811273,
        "text": "=)"
      }
    ]
  ],
  "53": [
    {
      "text": "С днем рождения, братик =)))"
    },
    [
      {
        "reply_to_uid": 0,
        "from_id": 4811273,
        "text": "Дядь)) Я не братик я племяш)))"
      },
      {
        "reply_to_uid": 0,
        "from_id": 4811273,
        "text": "Спасибо)"
      },
      {
        "reply_to_uid": 0,
        "from_id": 84785947,
        "text": "Дык мы вроде с тобой уже договорились, что на дядю я не тяну =))) Или я все таки дорос? =)))"
      },
      {
        "reply_to_uid": 0,
        "from_id": 4811273,
        "text": "Окей окей ) Будем братюнями))))"
      }
    ]
  ],
  "31": [
    {
      "text": "Стаф не отберут?"
    },
    [
      {
        "reply_to_uid": 0,
        "from_id": 4811273,
        "text": "Это в твоих интересах) Ты же хотел быть в говно)"
      },
      {
        "reply_to_uid": 0,
        "from_id": 1924095,
        "text": "есть гарантии? надо подговорить Ольгу чтобы ее не было, типо на следующий день должен быть кто-то свежий, и тогда проблем не будет."
      },
      {
        "reply_to_uid": 0,
        "from_id": 4811273,
        "text": "Да я думаю что все гуд будет)"
      },
      {
        "reply_to_uid": 0,
        "from_id": 4811273,
        "text": "ее напоить можно0"
      }
    ]
  ]
}