{
  "144": [
    {
      "text": "aionfree : Здарова братюня !1<br>aion.in.ua : Здарова , ахаха уеба ты че ревизию новую не поставил , у нас 3.0 уже давно !<br>aionfree : Хз , у меня ЕГЭ скоро как то не до этого..мб потроллим кого нибудь ?<br>aion.in.ua : Давай бугага<br>aionfree Добавил aionlegend в разговор<br>aionlegend : ??<br>aionfree : Это викторина Aion , ответьте на вопрос и получите 1к рублей<br>aionlegend : Oo го хуле<br>aion.in.ua : 150+150<br>aionlegend : ахахаххаха триста<br>aionfree : Отсоси у тракориста<br>aion.in.ua : ОТСОСИ У ТРАКТОРИСТА АХАХАХАХХА<br>aionlegend : пидоры , буду ддосить суки атвичаю !!!!!<br>aionlegend Покинул разговор<br>aionfree : До завтра братишь<br>aion.in.ua : бб"
    },
    [
      {
        "reply_to_uid": 0,
        "from_id": 161162784,
        "text": "спиздил у меня ахахха"
      }
    ]
  ],
  "17": [
    {
      "text": "AllMighty-наш камелот..."
    },
    [
      {
        "reply_to_uid": 0,
        "from_id": 28173233,
        "text": "Эпичнооооооооооо!!!!"
      },
      {
        "reply_to_uid": 0,
        "from_id": 79519458,
        "text": "обрыдаться   :`("
      }
    ]
  ],
  "146": [
    {
      "text": "Jockerz,Ranger 4.0 PvP vol.I"
    },
    [
      {
        "reply_to_uid": 0,
        "from_id": 9263905,
        "text": "эт на Делика я так понел?"
      }
    ]
  ],
  "51": [
    {
      "text": "Как вы считаете ,нужно ли менять сервер?"
    },
    [
      {
        "reply_to_uid": 0,
        "from_id": 79519458,
        "text": "фааак...<br>Тут Сань куда Легат , туда и лег  и я естесно"
      },
      {
        "reply_to_uid": 0,
        "from_id": 173476005,
        "text": "ГО ДОТА!!! Я СОЗДАЛ!"
      },
      {
        "reply_to_uid": 0,
        "from_id": 173476005,
        "text": "Не ну если админы будут дальше на жопе сидеть и ничего не пофиксят то надо валить)"
      },
      {
        "reply_to_uid": 0,
        "from_id": 12390480,
        "text": "Пока не собираюсь, не вижу альтернативы."
      },
      {
        "reply_to_uid": 0,
        "from_id": 97754733,
        "text": "Если ничего не измениться то когда серв умрет лишь вопрос вопрос времени. Решите куда то переходить я с вами."
      }
    ]
  ],
  "150": [
    {
      "text": ""
    },
    [
      {
        "reply_to_uid": 0,
        "from_id": 1927867,
        "text": "это когда было?"
      }
    ]
  ],
  "50": [
    {
      "text": ""
    },
    [
      {
        "reply_to_uid": 0,
        "from_id": 79519458,
        "text": "=DDDDD"
      },
      {
        "reply_to_uid": 0,
        "from_id": 79519458,
        "text": "Ох Олег Олег!"
      }
    ]
  ],
  "127": [
    {
      "text": "Всем привет ребята,13 числа,в субботу,легион AllMighty возращаеться туда, где был основан, на aion-free.ru открывается МЕДИУМ сервер,вместо харда,кому интересно-мне в личку в вк,Возродим то,силушку алмайтовскую?)"
    },
    [
      {
        "reply_to_uid": 0,
        "from_id": 1927867,
        "text": "несколько печальные воспоминания от фришки, а там фиг знает, что из него сделали"
      }
    ]
  ]
}