{
  "16": [
    {
      "text": "приежий одинокий ДАГЕСТАНЕЦ ишет свою вторую полавинку в группе 8-963-746-98-66"
    },
    [
      {
        "from_id": 83949491,
        "text": ")))))",
        "reply_to_uid": 0
      }
    ]
  ],
  "1": [
    {
      "text": "Хотели бы вы вечерние дискотеки в клубе Карелия???"
    },
    [
      {
        "from_id": 156126862,
        "text": "я из ДАГЕСТАНА живу в петрозаводск я хотел бы если согласились бы девушки",
        "reply_to_uid": 0
      }
    ]
  ],
  "5": [
    {
      "text": "Всем респект и клубу Карелия.Давайте поддержим реальную тему,всем за рание респект!!!"
    },
    [
      {
        "from_id": 26110300,
        "text": "я за)",
        "reply_to_uid": 0
      },
      {
        "from_id": 124301323,
        "text": "я тоже :)",
        "reply_to_uid": 0
      },
      {
        "from_id": 127460426,
        "text": "и я)",
        "reply_to_uid": 0
      },
      {
        "from_id": 74532524,
        "text": "Что то малова то жилающих!",
        "reply_to_uid": 0
      },
      {
        "from_id": 156126862,
        "text": "и я",
        "reply_to_uid": 0
      }
    ]
  ],
  "24": [
    {
      "text": "совсем тупые?<br>дискотека будет,только через 2-3 субботы<br>хватит заниматься ерундой"
    },
    [
      {
        "from_id": 18666015,
        "text": "тупые??? ещё какие???",
        "reply_to_uid": 0
      }
    ]
  ],
  "11": [
    {
      "text": "\"Верчении\" название исправьте!"
    },
    [
      {
        "from_id": 156126862,
        "text": "че пойдем месте?",
        "reply_to_uid": 0
      },
      {
        "from_id": 38371894,
        "text": "но...\"обязательно\"",
        "reply_to_uid": 0
      }
    ]
  ],
  "13": [
    {
      "text": "А одинокие девушки есть в группе?ищущие вторую половинку?"
    },
    [
      {
        "from_id": 38371894,
        "text": "пусто",
        "reply_to_uid": 0
      },
      {
        "from_id": 74532524,
        "text": "Печально!очень!",
        "reply_to_uid": 0
      },
      {
        "from_id": 83949491,
        "text": "Ну да))))) почти",
        "reply_to_uid": 0
      },
      {
        "from_id": 74532524,
        "text": "Почему почти?",
        "reply_to_uid": 0
      }
    ]
  ]
}