{
  "185": [
    {
      "text": "что с сервером"
    },
    [
      {
        "reply_to_uid": 0,
        "from_id": 137408086,
        "text": "Тех работы!"
      },
      {
        "reply_to_uid": 137408086,
        "from_id": 140815293,
        "text": "[id137408086|Никита], А поч предупреждения не было?"
      },
      {
        "reply_to_uid": 0,
        "from_id": 137408086,
        "text": "Так нужно!"
      },
      {
        "reply_to_uid": 0,
        "from_id": 137408086,
        "text": "к вечеру думаю включим"
      },
      {
        "reply_to_uid": 137408086,
        "from_id": 140815293,
        "text": "[id137408086|Никита], Оккей"
      },
      {
        "reply_to_uid": 0,
        "from_id": 137408086,
        "text": "так что ожидайте и не паникуйте!"
      },
      {
        "reply_to_uid": 0,
        "from_id": 35810431,
        "text": "а к скольким часам примерно"
      }
    ]
  ],
  "202": [
    {
      "text": "плин вы ваще гоните сёрв наночь закрыли придупреждать надо!!!!!!!!!"
    },
    [
      {
        "reply_to_uid": 0,
        "from_id": 43321240,
        "text": "Ну просто так сервер не отключают. Может снова провайдер подводит или серв уронили, а включить некому..."
      },
      {
        "reply_to_uid": 0,
        "from_id": 133046070,
        "text": "a donat vernut?kto znaet?"
      }
    ]
  ],
  "211": [
    {
      "text": "Сайт лежит, сервер лежит. И тишина... В группе рекламируют чужой сервер. Лол."
    },
    [
      {
        "reply_to_uid": 0,
        "from_id": 22126605,
        "text": "ну а что ты хотел?))"
      }
    ]
  ],
  "214": [
    {
      "text": "Помнится мне старый-добрый матч :3 <br>Когда со 2гр +6 можно было убить каждого, ну кроме танков :D<br><br>Жаль сервер вайпнули, а в скоре забили на него :С"
    },
    [
      {
        "reply_to_uid": 0,
        "from_id": 99042673,
        "text": "хихихихи я засветился)"
      },
      {
        "reply_to_uid": 0,
        "from_id": 44649279,
        "text": "и я в кадре о_О"
      },
      {
        "reply_to_uid": 0,
        "from_id": 44649279,
        "text": "ЗЫ: Тимур козъёль"
      }
    ]
  ]
}