{
  "188": [
    {
      "text": "Я не понимаю парней которые гуляют всю свою молодость, а потом ищут себе достойную жену, тихую и спокойную. Человек заслуживает ту,кем он сам является. Достойному достойную,а проституту проститутка. Все честно."
    },
    [
      {
        "text": "Молодцы",
        "from_id": 90490909,
        "reply_to_uid": 0
      }
    ]
  ],
  "69": [
    {
      "text": "А у вас было такое, что вот вроде и не любишь человека, а тебя к нему тянет?"
    },
    [
      {
        "text": "Да....а что с этим делать?",
        "from_id": 76396679,
        "reply_to_uid": 0
      },
      {
        "text": "терпеть)",
        "from_id": 133987691,
        "reply_to_uid": 0
      }
    ]
  ]
}