{
  "19": [
    {
      "text": "сегодня команда Дакар одержала победу над командой ОТИ МИФИ со счётом 5:0, набрав этим самым 15 очков в чемпионате. Поздравляем!"
    },
    [
      {
        "from_id": 80670034,
        "text": "Молодцы! Давайте дальше в том же духе!",
        "reply_to_uid": 0
      }
    ]
  ],
  "5": [
    {
      "text": "28 декабря 2011 года последний матч уходящего года, кто выйграет?"
    },
    [
      {
        "from_id": 62887346,
        "text": "сто пудово ДАКАР!!! я орать буду за вас :)",
        "reply_to_uid": 0
      },
      {
        "from_id": 52712072,
        "text": "давай кэп)",
        "reply_to_uid": 0
      },
      {
        "from_id": 62887346,
        "text": "всегда с вами)",
        "reply_to_uid": 0
      },
      {
        "from_id": 40091856,
        "text": "пацаны полюбомы мы затащим я даже падать не буду))))",
        "reply_to_uid": 0
      },
      {
        "from_id": 52712072,
        "text": ":D",
        "reply_to_uid": 0
      },
      {
        "from_id": 52712072,
        "text": "ты наверно хотел сказать что ты даже пить не будешь=))",
        "reply_to_uid": 0
      }
    ]
  ],
  "13": [
    {
      "text": "Мы выйграли 5:2, всех с победой поздравляю=)"
    },
    [
      {
        "from_id": 99804113,
        "text": "поздравляю:)",
        "reply_to_uid": 0
      },
      {
        "from_id": 52712072,
        "text": "Спасибо=)",
        "reply_to_uid": 0
      }
    ]
  ],
  "23": [
    {
      "text": "Завтра, 9 февраля. Состоится очередная игра команды Дакар против команды \"Торпедо\". Начало в 19:20!"
    },
    [
      {
        "from_id": 29225723,
        "text": "19:40 же?",
        "reply_to_uid": 0
      },
      {
        "from_id": 20705810,
        "text": "да,в 19:40",
        "reply_to_uid": 0
      }
    ]
  ]
}