{
  "162": [
    {
      "text": "Создать конкурс на розыгрыш Инвайтов ??"
    },
    [
      {
        "reply_to_uid": 0,
        "from_id": 56039078,
        "text": "дайте инвайт ник в стиме Lcste и ещё mail: misha120201@mail.ru"
      },
      {
        "reply_to_uid": 0,
        "from_id": 181276116,
        "text": "пожалуйста пригласите в доту 2, зблся уже =(<br>если что могу по скайпу играть :) <br>p.s. Песню кто то слышал?))<br>_1nnoy_ https://vk.com/audio181276116_210735431"
      },
      {
        "reply_to_uid": 0,
        "from_id": 224068728,
        "text": "дайте инвайт пожалуйста на эту почту срочно: htdnytfynt@gmail.com"
      },
      {
        "reply_to_uid": 0,
        "from_id": 161341566,
        "text": "Инвайт"
      }
    ]
  ],
  "157": [
    {
      "text": "Кто первый напишет комент к этой записи инвайт на доту БЕСПЛАТНО !"
    },
    [
      {
        "reply_to_uid": 0,
        "from_id": 75668066,
        "text": "Давай мне"
      },
      {
        "reply_to_uid": 0,
        "from_id": -33358487,
        "text": "Поздравляю !"
      },
      {
        "reply_to_uid": 162722813,
        "from_id": -33358487,
        "text": "Да есть"
      },
      {
        "reply_to_uid": 162722813,
        "from_id": 139356072,
        "text": "[id162722813|Дмитрий], есть"
      },
      {
        "reply_to_uid": 0,
        "from_id": 96406235,
        "text": "дайте инвайт  пожалуйста очень надо ! спасибо за рание"
      },
      {
        "reply_to_uid": 96406235,
        "from_id": 139356072,
        "text": "[id96406235|Лёша], Либо учавствуй в конкурсе либо покупай цена 10 рублей!"
      }
    ]
  ]
}