{
  "9": [
    {
      "text": "Варёные августы будут?"
    },
    [
      {
        "reply_to_uid": 0,
        "from_id": 60409585,
        "text": "ага...и очень много"
      }
    ]
  ],
  "2": [
    {
      "text": "я не знаю Жень получится или нет в связи с НГ"
    },
    [
      {
        "reply_to_uid": 0,
        "from_id": 60409585,
        "text": "жаль будет... ну а так подходи время начала только ведь в 19:00,так что ты можешь в 03:00 ночи уйти)))"
      }
    ]
  ],
  "4": [
    {
      "text": "а тебе самой не кажется что немножко пиздецово выходит?)))"
    },
    [
      {
        "reply_to_uid": 0,
        "from_id": 60409585,
        "text": "а что делать? мне кажется лучше так ,чем никак!!"
      }
    ]
  ],
  "1": [
    {
      "text": "можете написать причины своего отказа или причину почему вы не можете придти .... и что вас интересует ..."
    },
    [
      {
        "reply_to_uid": 0,
        "from_id": 4219412,
        "text": "подготовка к нг"
      },
      {
        "reply_to_uid": 0,
        "from_id": 60409585,
        "text": "это успеется,ты всю ночь готовиться будешь? я просто ифигеваю... меня уже терзают сомнения по поводу этого..."
      },
      {
        "reply_to_uid": 0,
        "from_id": 4219412,
        "text": "по поводу ночи незнаю, а организм к нг подготовить? :)"
      }
    ]
  ]
}